[
  {
    "id": "kochi",
    "city": "高知市",
    "prefecture": "高知県",
    "prefectureSlug": "kochi",
    "description": "太平洋の絶景とカツオの街",
    "themes": [
      "view",
      "food"
    ],
    "modelCourses": [
      "桂浜 → ひろめ市場 → 高知城",
      "日曜市 → 高知城 → はりまや橋 → ひろめ市場"
    ],
    "access": {
      "takamatsu": {
        "outbound": "高松 7:12発 → 特急南風3号 → 高知 9:43着",
        "return": "高知 17:26発 → 特急南風22号 → 高松 19:52着",
        "time": "約2時間30分",
        "price": "約6,000円（往復）",
        "ic": "利用可"
      },
      "okayama": {
        "outbound": "岡山 7:05発 → 特急南風1号 → 高知 9:43着",
        "return": "高知 17:26発 → 特急南風22号 → 岡山 19:55着",
        "time": "約2時間40分",
        "price": "約10,000円（往復）",
        "ic": "利用可"
      },
      "osaka": {
        "outbound": "大阪 7:30発 → 高速バス → 高知 12:00着",
        "return": "高知 16:00発 → 高速バス → 大阪 20:30着",
        "time": "約4時間30分",
        "price": "約7,400円（往復）",
        "ic": "不可（事前予約）"
      },
      "matsuyama": {
        "outbound": "松山 7:30発 → JR特急しおかぜ → 多度津乗換 → 特急南風 → 高知 10:30着",
        "return": "高知 16:30発 → 特急南風 → 多度津乗換 → JR特急いしづち → 松山 19:30着",
        "time": "約3時間",
        "price": "約8,500円（往復）",
        "ic": "利用可"
      }
    },
    "budgetLevel": 4,
    "region": "四国",
    "staySupport": [
      "daytrip",
      "1night"
    ],
    "transportType": "rail",
    "baseTravelHours": 3
  },
  {
    "id": "tokushima",
    "city": "徳島市",
    "prefecture": "徳島県",
    "prefectureSlug": "tokushima",
    "description": "阿波踊りの街と徳島ラーメン",
    "themes": [
      "food",
      "experience"
    ],
    "modelCourses": [
      "徳島ラーメン → 阿波踊り会館 → 眉山ロープウェイ",
      "眉山 → ひょうたん島クルーズ → 徳島ラーメン"
    ],
    "access": {
      "takamatsu": {
        "outbound": "高松 8:00発 → 特急うずしお5号 → 徳島 9:15着",
        "return": "徳島 18:00発 → 特急うずしお28号 → 高松 19:12着",
        "time": "約1時間15分",
        "price": "約3,000円（往復）",
        "ic": "利用可"
      },
      "osaka": {
        "outbound": "大阪 8:00発 → 高速バス → 徳島 10:40着",
        "return": "徳島 17:30発 → 高速バス → 大阪 20:10着",
        "time": "約2時間40分",
        "price": "約4,000円（往復）",
        "ic": "不可（事前予約）"
      },
      "kobe": {
        "outbound": "三ノ宮BT 8:20発 → 高速バス → 徳島 10:20着",
        "return": "徳島 17:30発 → 高速バス → 三ノ宮BT 19:30着",
        "time": "約2時間",
        "price": "約3,600円（往復）",
        "ic": "不可（事前予約）"
      }
    },
    "budgetLevel": 3,
    "region": "四国",
    "staySupport": [
      "daytrip"
    ],
    "transportType": "rail",
    "baseTravelHours": 1.5
  },
  {
    "id": "shodoshima",
    "city": "小豆島（土庄町）",
    "prefecture": "香川県",
    "prefectureSlug": "kagawa",
    "description": "エンジェルロードとオリーブの島",
    "themes": [
      "view",
      "experience"
    ],
    "modelCourses": [
      "エンジェルロード → オリーブ公園 → 海沿いカフェ",
      "寒霞渓ロープウェイ → 二十四の瞳映画村 → 醤油蔵通り"
    ],
    "access": {
      "takamatsu": {
        "outbound": "高松港 9:00発 → フェリー → 土庄港 10:00着",
        "return": "土庄港 17:00発 → フェリー → 高松港 18:00着",
        "time": "約1時間",
        "price": "約1,400円（往復）",
        "ic": "不可（現金のみ）"
      },
      "okayama": {
        "outbound": "新岡山港 9:00発 → フェリー → 土庄港 10:10着",
        "return": "土庄港 17:00発 → フェリー → 新岡山港 18:10着",
        "time": "約1時間10分",
        "price": "約2,100円（往復）",
        "ic": "不可（現金のみ）"
      }
    },
    "budgetLevel": 2,
    "region": "四国",
    "staySupport": [
      "daytrip",
      "1night"
    ],
    "transportType": "rail+car",
    "baseTravelHours": 2.5
  },
  {
    "id": "matsuyama",
    "city": "松山市",
    "prefecture": "愛媛県",
    "prefectureSlug": "ehime",
    "description": "道後温泉と文学の街",
    "themes": [
      "experience",
      "food"
    ],
    "modelCourses": [
      "道後温泉本館 → 松山城 → 大街道で鯛めし",
      "松山城 → 坊っちゃんカラクリ時計 → 道後温泉 → 鯛めし"
    ],
    "access": {
      "takamatsu": {
        "outbound": "高松 7:27発 → 特急いしづち3号 → 松山 10:03着",
        "return": "松山 17:25発 → 特急いしづち26号 → 高松 19:56着",
        "time": "約2時間30分",
        "price": "約6,500円（往復）",
        "ic": "利用可"
      },
      "hiroshima": {
        "outbound": "広島港 8:00発 → スーパージェット → 松山観光港 9:10着",
        "return": "松山観光港 17:30発 → スーパージェット → 広島港 18:40着",
        "time": "約1時間10分",
        "price": "約8,600円（往復）",
        "ic": "不可（窓口購入）"
      },
      "okayama": {
        "outbound": "岡山 7:05発 → 特急しおかぜ1号 → 松山 9:45着",
        "return": "松山 17:25発 → 特急しおかぜ26号 → 岡山 20:02着",
        "time": "約2時間40分",
        "price": "約7,400円（往復）",
        "ic": "利用可"
      }
    },
    "budgetLevel": 4,
    "region": "四国",
    "staySupport": [
      "daytrip",
      "1night"
    ],
    "transportType": "rail",
    "baseTravelHours": 2.5
  },
  {
    "id": "kotohira",
    "city": "琴平町",
    "prefecture": "香川県",
    "prefectureSlug": "kagawa",
    "description": "金刀比羅宮の石段参りと讃岐うどん",
    "themes": [
      "experience",
      "food"
    ],
    "modelCourses": [
      "金刀比羅宮（石段785段） → 参道で讃岐うどん → 旧金毘羅大芝居",
      "中野うどん学校（うどん作り体験） → 金刀比羅宮 → 参道散策"
    ],
    "access": {
      "takamatsu": {
        "outbound": "高松 8:15発 → JR土讃線 → 琴平 9:12着",
        "return": "琴平 17:30発 → JR土讃線 → 高松 18:25着",
        "time": "約1時間",
        "price": "約1,700円（往復）",
        "ic": "利用可"
      },
      "okayama": {
        "outbound": "岡山 8:05発 → 特急南風3号 → 琴平 9:12着",
        "return": "琴平 17:42発 → 特急南風20号 → 岡山 18:55着",
        "time": "約1時間10分",
        "price": "約5,000円（往復）",
        "ic": "利用可"
      },
      "kochi": {
        "outbound": "高知 8:30発 → JR土讃線特急 → 琴平 9:40着",
        "return": "琴平 17:30発 → JR土讃線特急 → 高知 18:40着",
        "time": "約1時間10分",
        "price": "約3,200円（往復）",
        "ic": "利用可"
      }
    },
    "budgetLevel": 2,
    "region": "四国",
    "staySupport": [
      "daytrip"
    ],
    "transportType": "rail",
    "baseTravelHours": 1.5
  },
  {
    "id": "naruto",
    "city": "鳴門市",
    "prefecture": "徳島県",
    "prefectureSlug": "tokushima",
    "description": "渦潮と大塚国際美術館",
    "themes": [
      "view",
      "experience"
    ],
    "modelCourses": [
      "渦の道（渦潮見学） → 大塚国際美術館 → 鳴門わかめ料理",
      "うずしお観潮船 → 大塚国際美術館 → 鳴門海峡展望台"
    ],
    "access": {
      "takamatsu": {
        "outbound": "高松 8:00発 → 特急うずしお → 徳島乗換 → 鳴門 10:00着",
        "return": "鳴門 17:30発 → 徳島乗換 → 特急うずしお → 高松 19:30着",
        "time": "約2時間",
        "price": "約4,000円（往復）",
        "ic": "一部区間のみ"
      }
    },
    "budgetLevel": 3,
    "region": "四国",
    "staySupport": [
      "daytrip"
    ],
    "transportType": "rail",
    "baseTravelHours": 1.5
  },
  {
    "id": "iyakei",
    "city": "祖谷渓（三好市）",
    "prefecture": "徳島県",
    "prefectureSlug": "tokushima",
    "description": "日本三大秘境のかずら橋と渓谷美",
    "themes": [
      "view"
    ],
    "modelCourses": [
      "祖谷のかずら橋 → 小便小僧展望台 → 大歩危峡遊覧船",
      "大歩危峡 → かずら橋 → 祖谷温泉"
    ],
    "access": {
      "takamatsu": {
        "outbound": "高松 7:12発 → 特急南風3号 → 大歩危 8:55着 → バス → 祖谷",
        "return": "祖谷 → バス → 大歩危 16:50発 → 特急南風 → 高松 18:30着",
        "time": "約2時間30分（バス含む）",
        "price": "約5,500円（往復・バス別）",
        "ic": "JR区間のみ利用可"
      },
      "kochi": {
        "outbound": "高知 7:58発 → 特急南風 → 大歩危 8:55着 → バス → 祖谷",
        "return": "祖谷 → バス → 大歩危 16:50発 → 特急南風 → 高知 17:50着",
        "time": "約1時間30分（バス含む）",
        "price": "約3,800円（往復・バス別）",
        "ic": "JR区間のみ利用可"
      }
    },
    "budgetLevel": 3,
    "region": "四国",
    "staySupport": [
      "daytrip",
      "1night"
    ],
    "transportType": "rail+car",
    "baseTravelHours": 4
  },
  {
    "id": "naoshima",
    "city": "直島",
    "prefecture": "香川県",
    "prefectureSlug": "kagawa",
    "description": "アートの島・草間彌生のかぼちゃ",
    "themes": [
      "experience",
      "view"
    ],
    "modelCourses": [
      "地中美術館 → 李禹煥美術館 → 黄かぼちゃ → ベネッセハウス",
      "家プロジェクト（本村地区） → ANDO MUSEUM → 赤かぼちゃ → 海沿い散策"
    ],
    "access": {
      "takamatsu": {
        "outbound": "高松港 8:12発 → フェリー → 直島（宮浦港）9:02着",
        "return": "直島（宮浦港）17:35発 → フェリー → 高松港 18:25着",
        "time": "約50分",
        "price": "約1,060円（往復）",
        "ic": "不可（現金のみ）"
      },
      "okayama": {
        "outbound": "宇野港 9:22発 → フェリー → 直島（宮浦港）9:42着",
        "return": "直島（宮浦港）17:00発 → フェリー → 宇野港 17:20着",
        "time": "約20分（宇野港から）",
        "price": "約600円（往復・宇野〜直島）",
        "ic": "不可（現金のみ）"
      }
    },
    "budgetLevel": 1,
    "region": "四国",
    "staySupport": [
      "daytrip",
      "1night"
    ],
    "transportType": "rail+car",
    "baseTravelHours": 2
  },
  {
    "id": "kyoto",
    "city": "京都",
    "prefecture": "京都府",
    "prefectureSlug": "kyoto",
    "description": "千年の古都と寺社仏閣",
    "themes": [
      "view",
      "experience"
    ],
    "modelCourses": [
      "伏見稲荷大社 → 清水寺 → 祇園散策 → 錦市場",
      "金閣寺 → 龍安寺 → 嵐山竹林 → 渡月橋",
      "銀閣寺 → 哲学の道 → 南禅寺 → 蹴上インクライン"
    ],
    "access": {
      "osaka": {
        "outbound": "大阪 8:00発 → JR新快速 → 京都 8:29着",
        "return": "京都 18:30発 → JR新快速 → 大阪 18:59着",
        "time": "約30分",
        "price": "約1,160円（往復）",
        "ic": "利用可"
      },
      "nagoya": {
        "outbound": "名古屋 8:00発 → 新幹線のぞみ → 京都 8:35着",
        "return": "京都 18:30発 → 新幹線のぞみ → 名古屋 19:05着",
        "time": "約35分",
        "price": "約5,500円（往復・自由席）",
        "ic": "利用可"
      },
      "tokyo": {
        "outbound": "東京 7:33発 → 新幹線のぞみ → 京都 9:48着",
        "return": "京都 18:16発 → 新幹線のぞみ → 東京 20:30着",
        "time": "約2時間15分",
        "price": "約13,600円（往復・自由席）",
        "ic": "利用可"
      },
      "kobe": {
        "outbound": "三ノ宮 8:00発 → JR新快速 → 京都 8:51着",
        "return": "京都 18:30発 → JR新快速 → 三ノ宮 19:21着",
        "time": "約51分",
        "price": "約2,200円（往復）",
        "ic": "利用可"
      },
      "kanazawa": {
        "outbound": "金沢 8:00発 → 特急サンダーバード → 京都 10:09着",
        "return": "京都 17:50発 → 特急サンダーバード → 金沢 19:59着",
        "time": "約2時間10分",
        "price": "約7,500円（往復）",
        "ic": "利用可"
      }
    },
    "budgetLevel": 3,
    "region": "近畿",
    "staySupport": [
      "daytrip",
      "1night"
    ],
    "transportType": "rail",
    "baseTravelHours": 1.5
  },
  {
    "id": "nara",
    "city": "奈良",
    "prefecture": "奈良県",
    "prefectureSlug": "nara",
    "description": "大仏と鹿の古都",
    "themes": [
      "view",
      "experience"
    ],
    "modelCourses": [
      "東大寺（大仏殿） → 奈良公園で鹿と散策 → 春日大社 → ならまち",
      "興福寺 → 奈良公園 → 若草山 → 東大寺二月堂（夕景）"
    ],
    "access": {
      "osaka": {
        "outbound": "大阪難波 8:10発 → 近鉄特急 → 近鉄奈良 8:47着",
        "return": "近鉄奈良 18:20発 → 近鉄特急 → 大阪難波 18:57着",
        "time": "約37分",
        "price": "約1,200円（往復）",
        "ic": "利用可"
      },
      "kyoto": {
        "outbound": "京都 8:30発 → 近鉄特急 → 近鉄奈良 9:04着",
        "return": "近鉄奈良 18:00発 → 近鉄特急 → 京都 18:34着",
        "time": "約35分",
        "price": "約1,300円（往復）",
        "ic": "利用可"
      },
      "kobe": {
        "outbound": "三ノ宮 8:15発 → 阪神 → 大阪難波乗換 → 近鉄 → 近鉄奈良 9:25着",
        "return": "近鉄奈良 18:00発 → 近鉄 → 大阪難波 → 阪神 → 三ノ宮 19:10着",
        "time": "約1時間10分",
        "price": "約2,000円（往復）",
        "ic": "利用可"
      },
      "nagoya": {
        "outbound": "近鉄名古屋 8:00発 → 近鉄特急 → 大和八木乗換 → 近鉄奈良 10:10着",
        "return": "近鉄奈良 17:30発 → 大和八木乗換 → 近鉄特急 → 近鉄名古屋 19:40着",
        "time": "約2時間10分",
        "price": "約5,000円（往復）",
        "ic": "利用可"
      }
    },
    "budgetLevel": 2,
    "region": "近畿",
    "staySupport": [
      "daytrip"
    ],
    "transportType": "rail",
    "baseTravelHours": 1
  },
  {
    "id": "kobe",
    "city": "神戸",
    "prefecture": "兵庫県",
    "prefectureSlug": "hyogo",
    "description": "港町グルメと異人館の街並み",
    "themes": [
      "food",
      "view"
    ],
    "modelCourses": [
      "北野異人館街 → 南京町（中華街） → メリケンパーク → ハーバーランド",
      "三宮 → 生田神社 → 元町商店街 → 神戸牛ランチ → 神戸ポートタワー"
    ],
    "access": {
      "osaka": {
        "outbound": "大阪 8:15発 → JR新快速 → 三ノ宮 8:36着",
        "return": "三ノ宮 18:45発 → JR新快速 → 大阪 19:06着",
        "time": "約21分",
        "price": "約820円（往復）",
        "ic": "利用可"
      },
      "kyoto": {
        "outbound": "京都 8:00発 → JR新快速 → 三ノ宮 8:51着",
        "return": "三ノ宮 18:30発 → JR新快速 → 京都 19:21着",
        "time": "約51分",
        "price": "約2,200円（往復）",
        "ic": "利用可"
      }
    },
    "budgetLevel": 2,
    "region": "近畿",
    "staySupport": [
      "daytrip"
    ],
    "transportType": "rail",
    "baseTravelHours": 1
  },
  {
    "id": "himeji",
    "city": "姫路",
    "prefecture": "兵庫県",
    "prefectureSlug": "hyogo",
    "description": "世界遺産・白鷺城と好古園",
    "themes": [
      "view"
    ],
    "modelCourses": [
      "姫路城 → 好古園（日本庭園） → 大手前商店街で姫路おでん",
      "姫路城 → 姫路市立動物園 → 書写山圓教寺（ロープウェイ）"
    ],
    "access": {
      "osaka": {
        "outbound": "大阪 8:00発 → JR新快速 → 姫路 9:02着",
        "return": "姫路 18:00発 → JR新快速 → 大阪 19:02着",
        "time": "約1時間",
        "price": "約3,040円（往復）",
        "ic": "利用可"
      },
      "kobe": {
        "outbound": "三ノ宮 8:15発 → JR新快速 → 姫路 8:55着",
        "return": "姫路 18:00発 → JR新快速 → 三ノ宮 18:40着",
        "time": "約40分",
        "price": "約1,900円（往復）",
        "ic": "利用可"
      },
      "okayama": {
        "outbound": "岡山 8:20発 → JR山陽本線 → 姫路 9:50着",
        "return": "姫路 18:00発 → JR山陽本線 → 岡山 19:30着",
        "time": "約1時間30分",
        "price": "約3,700円（往復）",
        "ic": "利用可"
      }
    },
    "budgetLevel": 2,
    "region": "近畿",
    "staySupport": [
      "daytrip"
    ],
    "transportType": "rail",
    "baseTravelHours": 1.5
  },
  {
    "id": "wakayama",
    "city": "和歌山市",
    "prefecture": "和歌山県",
    "prefectureSlug": "wakayama",
    "description": "和歌山城とラーメンの街",
    "themes": [
      "food",
      "view"
    ],
    "modelCourses": [
      "和歌山城 → 和歌山ラーメン → 紀三井寺 → 和歌浦",
      "黒潮市場 → ポルトヨーロッパ → 和歌山ラーメン → 和歌山城"
    ],
    "access": {
      "osaka": {
        "outbound": "大阪 7:45発 → 特急くろしお1号 → 和歌山 8:57着",
        "return": "和歌山 18:06発 → 特急くろしお28号 → 大阪 19:18着",
        "time": "約1時間12分",
        "price": "約4,800円（往復）",
        "ic": "利用可"
      }
    },
    "budgetLevel": 3,
    "region": "近畿",
    "staySupport": [
      "daytrip"
    ],
    "transportType": "rail",
    "baseTravelHours": 2
  },
  {
    "id": "koyasan",
    "city": "高野山",
    "prefecture": "和歌山県",
    "prefectureSlug": "wakayama",
    "description": "世界遺産の聖地・奥之院と精進料理",
    "themes": [
      "experience",
      "view"
    ],
    "modelCourses": [
      "奥之院 → 金剛峯寺 → 壇上伽藍 → 精進料理ランチ",
      "大門 → 壇上伽藍 → 金剛峯寺 → 奥之院ナイトツアー"
    ],
    "access": {
      "osaka": {
        "outbound": "なんば 7:50発 → 南海特急こうや → 極楽橋 → ケーブル → 高野山 9:33着",
        "return": "高野山 17:15発 → ケーブル → 南海特急 → なんば 19:07着",
        "time": "約1時間45分",
        "price": "約5,200円（往復）",
        "ic": "南海線のみ利用可"
      }
    },
    "budgetLevel": 3,
    "region": "近畿",
    "staySupport": [
      "daytrip",
      "1night"
    ],
    "transportType": "rail",
    "baseTravelHours": 3
  },
  {
    "id": "arima",
    "city": "有馬温泉",
    "prefecture": "兵庫県",
    "prefectureSlug": "hyogo",
    "description": "日本三名泉・金泉銀泉の温泉街",
    "themes": [
      "experience",
      "food"
    ],
    "modelCourses": [
      "金の湯 → 温泉街散策 → 炭酸せんべい → 銀の湯 → 有馬グルメ",
      "瑞宝寺公園 → 有馬玩具博物館 → 金の湯 → 温泉街で食べ歩き"
    ],
    "access": {
      "osaka": {
        "outbound": "大阪 8:30発 → JR → 三ノ宮 → 神戸電鉄 → 有馬温泉 9:50着",
        "return": "有馬温泉 17:30発 → 神戸電鉄 → 三ノ宮 → JR → 大阪 18:50着",
        "time": "約1時間20分",
        "price": "約2,800円（往復）",
        "ic": "利用可"
      },
      "kobe": {
        "outbound": "三ノ宮 8:30発 → 神戸電鉄 → 有馬温泉 9:10着",
        "return": "有馬温泉 17:30発 → 神戸電鉄 → 三ノ宮 18:10着",
        "time": "約40分",
        "price": "約1,400円（往復）",
        "ic": "利用可"
      },
      "kyoto": {
        "outbound": "京都 8:00発 → JR新快速 → 三ノ宮 → 神戸電鉄 → 有馬温泉 9:50着",
        "return": "有馬温泉 17:00発 → 神戸電鉄 → 三ノ宮 → JR新快速 → 京都 18:50着",
        "time": "約1時間50分",
        "price": "約3,600円（往復）",
        "ic": "利用可"
      }
    },
    "budgetLevel": 2,
    "region": "近畿",
    "staySupport": [
      "daytrip"
    ],
    "transportType": "rail",
    "baseTravelHours": 1
  },
  {
    "id": "kamakura",
    "city": "鎌倉",
    "prefecture": "神奈川県",
    "prefectureSlug": "kanagawa",
    "description": "大仏と古都の海沿い散策",
    "themes": [
      "view",
      "experience"
    ],
    "modelCourses": [
      "鶴岡八幡宮 → 小町通り → 高徳院（大仏） → 長谷寺 → 由比ヶ浜",
      "北鎌倉（円覚寺・明月院） → 建長寺 → 鶴岡八幡宮 → 小町通りグルメ",
      "江ノ電で長谷 → 大仏 → 江ノ島 → 湘南の海沿いカフェ"
    ],
    "access": {
      "tokyo": {
        "outbound": "東京 8:15発 → JR横須賀線 → 鎌倉 9:13着",
        "return": "鎌倉 18:00発 → JR横須賀線 → 東京 18:58着",
        "time": "約58分",
        "price": "約1,900円（往復）",
        "ic": "利用可"
      },
      "yokohama": {
        "outbound": "横浜 8:30発 → JR横須賀線 → 鎌倉 8:54着",
        "return": "鎌倉 18:00発 → JR横須賀線 → 横浜 18:24着",
        "time": "約24分",
        "price": "約700円（往復）",
        "ic": "利用可"
      }
    },
    "budgetLevel": 1,
    "region": "関東",
    "staySupport": [
      "daytrip"
    ],
    "transportType": "rail",
    "baseTravelHours": 1
  },
  {
    "id": "hakone",
    "city": "箱根",
    "prefecture": "神奈川県",
    "prefectureSlug": "kanagawa",
    "description": "富士山の絶景と温泉リゾート",
    "themes": [
      "view",
      "experience"
    ],
    "modelCourses": [
      "箱根湯本 → 登山電車 → 強羅 → ロープウェイ → 大涌谷 → 芦ノ湖遊覧",
      "箱根湯本温泉街散策 → 彫刻の森美術館 → 強羅公園 → 大涌谷"
    ],
    "access": {
      "tokyo": {
        "outbound": "新宿 7:30発 → 小田急ロマンスカー → 箱根湯本 9:03着",
        "return": "箱根湯本 18:18発 → 小田急ロマンスカー → 新宿 19:50着",
        "time": "約1時間33分",
        "price": "約4,600円（往復・ロマンスカー）",
        "ic": "利用可"
      },
      "yokohama": {
        "outbound": "横浜 8:00発 → 小田急線（町田乗換） → 箱根湯本 9:40着",
        "return": "箱根湯本 18:00発 → 小田急線 → 横浜 19:40着",
        "time": "約1時間40分",
        "price": "約3,000円（往復）",
        "ic": "利用可"
      }
    },
    "budgetLevel": 3,
    "region": "関東",
    "staySupport": [
      "daytrip",
      "1night"
    ],
    "transportType": "rail",
    "baseTravelHours": 2
  },
  {
    "id": "nikko",
    "city": "日光",
    "prefecture": "栃木県",
    "prefectureSlug": "tochigi",
    "description": "世界遺産の社寺と華厳の滝",
    "themes": [
      "view",
      "experience"
    ],
    "modelCourses": [
      "東照宮 → 輪王寺 → 二荒山神社 → 神橋 → 日光グルメ",
      "いろは坂 → 中禅寺湖 → 華厳の滝 → 東照宮"
    ],
    "access": {
      "tokyo": {
        "outbound": "浅草 7:30発 → 東武特急リバティ → 東武日光 9:22着",
        "return": "東武日光 17:35発 → 東武特急リバティ → 浅草 19:27着",
        "time": "約1時間52分",
        "price": "約5,400円（往復・特急）",
        "ic": "東武線のみ利用可"
      },
      "sendai": {
        "outbound": "仙台 7:40発 → 東北新幹線 → 宇都宮 → JR日光線 → 日光 10:00着",
        "return": "日光 17:00発 → JR日光線 → 宇都宮 → 東北新幹線 → 仙台 19:10着",
        "time": "約2時間20分",
        "price": "約10,000円（往復）",
        "ic": "利用可"
      },
      "yokohama": {
        "outbound": "横浜 7:20発 → JR湘南新宿ライン → 大宮乗換 → 東武日光線 → 東武日光 10:10着",
        "return": "東武日光 17:00発 → 東武日光線 → 大宮 → JR → 横浜 19:50着",
        "time": "約2時間50分",
        "price": "約5,800円（往復）",
        "ic": "利用可"
      }
    },
    "budgetLevel": 4,
    "region": "関東",
    "staySupport": [
      "daytrip",
      "1night"
    ],
    "transportType": "rail",
    "baseTravelHours": 2.5
  },
  {
    "id": "kawagoe",
    "city": "川越",
    "prefecture": "埼玉県",
    "prefectureSlug": "saitama",
    "description": "小江戸の蔵造りと菓子屋横丁",
    "themes": [
      "experience",
      "food"
    ],
    "modelCourses": [
      "蔵造りの町並み → 時の鐘 → 菓子屋横丁 → 氷川神社",
      "喜多院 → 蔵造りの町並み → 菓子屋横丁 → 川越氷川神社（縁結び）"
    ],
    "access": {
      "tokyo": {
        "outbound": "池袋 8:00発 → 東武東上線急行 → 川越 8:32着",
        "return": "川越 18:00発 → 東武東上線急行 → 池袋 18:32着",
        "time": "約32分",
        "price": "約960円（往復）",
        "ic": "利用可"
      }
    },
    "budgetLevel": 1,
    "region": "関東",
    "staySupport": [
      "daytrip"
    ],
    "transportType": "rail",
    "baseTravelHours": 1
  },
  {
    "id": "yokohama",
    "city": "横浜中華街",
    "prefecture": "神奈川県",
    "prefectureSlug": "kanagawa",
    "description": "日本最大の中華街と港町",
    "themes": [
      "food"
    ],
    "modelCourses": [
      "中華街で食べ歩き → 山下公園 → 赤レンガ倉庫 → みなとみらい",
      "中華街ランチ → 元町商店街 → 港の見える丘公園 → 山下公園"
    ],
    "access": {
      "tokyo": {
        "outbound": "東京 8:20発 → JR東海道線 → 横浜 8:46着 → みなとみらい線 → 元町・中華街 9:00着",
        "return": "元町・中華街 18:30発 → みなとみらい線 → 横浜 → JR → 東京 19:15着",
        "time": "約40分",
        "price": "約1,300円（往復）",
        "ic": "利用可"
      }
    },
    "budgetLevel": 1,
    "region": "関東",
    "staySupport": [
      "daytrip"
    ],
    "transportType": "rail",
    "baseTravelHours": 0.5
  },
  {
    "id": "chichibu",
    "city": "秩父",
    "prefecture": "埼玉県",
    "prefectureSlug": "saitama",
    "description": "三十四観音霊場と長瀞の自然",
    "themes": [
      "view",
      "experience"
    ],
    "modelCourses": [
      "長瀞ライン下り → 宝登山神社 → 秩父神社 → わらじかつ丼",
      "三峯神社 → 秩父まつり会館 → 秩父神社 → 西武秩父駅前温泉"
    ],
    "access": {
      "tokyo": {
        "outbound": "池袋 7:30発 → 西武特急ラビュー → 西武秩父 8:48着",
        "return": "西武秩父 18:05発 → 西武特急ラビュー → 池袋 19:23着",
        "time": "約1時間18分",
        "price": "約3,400円（往復・特急）",
        "ic": "利用可"
      },
      "yokohama": {
        "outbound": "横浜 7:20発 → JR湘南新宿ライン → 池袋乗換 → 西武特急ラビュー → 西武秩父 9:23着",
        "return": "西武秩父 18:05発 → 西武特急ラビュー → 池袋 → JR → 横浜 20:00着",
        "time": "約2時間",
        "price": "約4,200円（往復）",
        "ic": "利用可"
      }
    },
    "budgetLevel": 3,
    "region": "関東",
    "staySupport": [
      "daytrip"
    ],
    "transportType": "rail",
    "baseTravelHours": 2.5
  },
  {
    "id": "kurashiki",
    "city": "倉敷",
    "prefecture": "岡山県",
    "prefectureSlug": "okayama",
    "description": "美観地区の白壁と大原美術館",
    "themes": [
      "view",
      "experience"
    ],
    "modelCourses": [
      "美観地区 → 大原美術館 → 倉敷川沿い散策 → アイビースクエア",
      "大原美術館 → 日本郷土玩具館 → 倉敷デニムストリート → 美観地区カフェ"
    ],
    "access": {
      "okayama": {
        "outbound": "岡山 8:42発 → JR山陽本線 → 倉敷 8:59着",
        "return": "倉敷 18:15発 → JR山陽本線 → 岡山 18:32着",
        "time": "約17分",
        "price": "約660円（往復）",
        "ic": "利用可"
      },
      "takamatsu": {
        "outbound": "高松 7:25発 → 快速マリンライナー → 岡山乗換 → 倉敷 9:00着",
        "return": "倉敷 18:15発 → 岡山乗換 → 快速マリンライナー → 高松 19:40着",
        "time": "約1時間35分",
        "price": "約3,200円（往復）",
        "ic": "利用可"
      },
      "hiroshima": {
        "outbound": "広島 8:00発 → 新幹線こだま → 新倉敷 8:35着 → 倉敷 8:45着",
        "return": "新倉敷 18:00発 → 新幹線こだま → 広島 18:35着",
        "time": "約45分",
        "price": "約5,000円（往復・自由席）",
        "ic": "利用可"
      },
      "matsue": {
        "outbound": "松江 7:30発 → 特急やくも → 岡山乗換 → 倉敷 10:30着",
        "return": "倉敷 17:00発 → 岡山乗換 → 特急やくも → 松江 20:00着",
        "time": "約3時間",
        "price": "約7,500円（往復）",
        "ic": "利用可"
      }
    },
    "budgetLevel": 3,
    "region": "中国",
    "staySupport": [
      "daytrip"
    ],
    "transportType": "rail",
    "baseTravelHours": 1.5
  },
  {
    "id": "onomichi",
    "city": "尾道",
    "prefecture": "広島県",
    "prefectureSlug": "hiroshima",
    "description": "坂の街と尾道ラーメンとしまなみ海道",
    "themes": [
      "view",
      "food"
    ],
    "modelCourses": [
      "千光寺ロープウェイ → 千光寺公園 → 猫の細道 → 尾道ラーメン",
      "しまなみ海道サイクリング → 因島 → 尾道ラーメン → 千光寺"
    ],
    "access": {
      "okayama": {
        "outbound": "岡山 8:17発 → JR山陽本線 → 尾道 9:46着",
        "return": "尾道 17:50発 → JR山陽本線 → 岡山 19:20着",
        "time": "約1時間30分",
        "price": "約3,200円（往復）",
        "ic": "利用可"
      },
      "hiroshima": {
        "outbound": "広島 8:20発 → JR山陽本線 → 尾道 9:50着",
        "return": "尾道 17:50発 → JR山陽本線 → 広島 19:20着",
        "time": "約1時間30分",
        "price": "約3,200円（往復）",
        "ic": "利用可"
      }
    },
    "budgetLevel": 2,
    "region": "中国",
    "staySupport": [
      "daytrip",
      "1night"
    ],
    "transportType": "rail",
    "baseTravelHours": 2
  },
  {
    "id": "hiroshima",
    "city": "広島市",
    "prefecture": "広島県",
    "prefectureSlug": "hiroshima",
    "description": "平和記念公園と広島お好み焼き",
    "themes": [
      "experience",
      "food"
    ],
    "modelCourses": [
      "平和記念公園 → 原爆ドーム → 広島お好み焼き → 縮景園",
      "宮島口 → 厳島神社 → 広島市内 → お好み焼き村"
    ],
    "access": {
      "okayama": {
        "outbound": "岡山 8:08発 → 新幹線のぞみ → 広島 8:46着",
        "return": "広島 18:15発 → 新幹線のぞみ → 岡山 18:53着",
        "time": "約38分（新幹線）",
        "price": "約7,000円（往復・自由席）",
        "ic": "利用可"
      },
      "fukuoka": {
        "outbound": "博多 8:00発 → 新幹線のぞみ → 広島 9:05着",
        "return": "広島 18:15発 → 新幹線のぞみ → 博多 19:20着",
        "time": "約1時間5分（新幹線）",
        "price": "約9,000円（往復・自由席）",
        "ic": "利用可"
      }
    },
    "budgetLevel": 4,
    "region": "中国",
    "staySupport": [
      "daytrip",
      "1night"
    ],
    "transportType": "shinkansen",
    "baseTravelHours": 2
  },
  {
    "id": "dazaifu",
    "city": "太宰府",
    "prefecture": "福岡県",
    "prefectureSlug": "fukuoka",
    "description": "学問の神様と梅ヶ枝餅",
    "themes": [
      "experience"
    ],
    "modelCourses": [
      "太宰府天満宮 → 参道で梅ヶ枝餅 → 九州国立博物館 → 光明禅寺",
      "竈門神社 → 太宰府天満宮 → 参道散策 → スターバックス太宰府店"
    ],
    "access": {
      "fukuoka": {
        "outbound": "天神 8:30発 → 西鉄電車 → 太宰府 9:05着",
        "return": "太宰府 17:30発 → 西鉄電車 → 天神 18:05着",
        "time": "約35分",
        "price": "約820円（往復）",
        "ic": "利用可"
      },
      "kumamoto": {
        "outbound": "熊本 8:00発 → 九州新幹線 → 博多 → 西鉄 → 太宰府 9:45着",
        "return": "太宰府 17:00発 → 西鉄 → 博多 → 九州新幹線 → 熊本 18:40着",
        "time": "約1時間45分",
        "price": "約6,000円（往復）",
        "ic": "利用可"
      }
    },
    "budgetLevel": 2,
    "region": "九州",
    "staySupport": [
      "daytrip"
    ],
    "transportType": "rail",
    "baseTravelHours": 1
  },
  {
    "id": "yanagawa",
    "city": "柳川",
    "prefecture": "福岡県",
    "prefectureSlug": "fukuoka",
    "description": "川下りとうなぎのせいろ蒸し",
    "themes": [
      "view",
      "food"
    ],
    "modelCourses": [
      "柳川川下り → 御花（立花家旧邸） → うなぎのせいろ蒸し",
      "川下り → 北原白秋生家 → 柳川散策 → うなぎランチ"
    ],
    "access": {
      "fukuoka": {
        "outbound": "天神 8:20発 → 西鉄特急 → 柳川 9:08着",
        "return": "柳川 17:45発 → 西鉄特急 → 天神 18:33着",
        "time": "約48分",
        "price": "約1,700円（往復）",
        "ic": "利用可"
      },
      "kumamoto": {
        "outbound": "熊本 8:00発 → 九州新幹線 → 新大牟田 → 西鉄 → 柳川 9:30着",
        "return": "柳川 17:30発 → 西鉄 → 新大牟田 → 九州新幹線 → 熊本 19:00着",
        "time": "約1時間30分",
        "price": "約4,500円（往復）",
        "ic": "利用可"
      }
    },
    "budgetLevel": 2,
    "region": "九州",
    "staySupport": [
      "daytrip"
    ],
    "transportType": "rail",
    "baseTravelHours": 1.5
  },
  {
    "id": "mojiko",
    "city": "門司港",
    "prefecture": "福岡県",
    "prefectureSlug": "fukuoka",
    "description": "レトロな港町と焼きカレー",
    "themes": [
      "food",
      "view"
    ],
    "modelCourses": [
      "門司港レトロ地区 → 焼きカレーランチ → 関門海峡ミュージアム → 関門トンネル人道",
      "九州鉄道記念館 → 門司港駅舎 → 焼きカレー → 関門連絡船で下関"
    ],
    "access": {
      "fukuoka": {
        "outbound": "博多 8:15発 → JR鹿児島本線快速 → 門司港 9:42着",
        "return": "門司港 17:45発 → JR快速 → 博多 19:10着",
        "time": "約1時間25分",
        "price": "約3,100円（往復）",
        "ic": "利用可"
      }
    },
    "budgetLevel": 2,
    "region": "九州",
    "staySupport": [
      "daytrip"
    ],
    "transportType": "rail",
    "baseTravelHours": 1.5
  },
  {
    "id": "beppu",
    "city": "別府",
    "prefecture": "大分県",
    "prefectureSlug": "oita",
    "description": "地獄めぐりと日本一の温泉郷",
    "themes": [
      "experience",
      "view"
    ],
    "modelCourses": [
      "地獄めぐり（海地獄・血の池地獄） → 別府温泉 → 明礬温泉 → 地獄蒸し",
      "鉄輪温泉 → 地獄蒸し工房 → 地獄めぐり → 砂湯"
    ],
    "access": {
      "fukuoka": {
        "outbound": "博多 8:24発 → 特急ソニック11号 → 別府 10:14着",
        "return": "別府 17:47発 → 特急ソニック42号 → 博多 19:43着",
        "time": "約1時間50分",
        "price": "約6,200円（往復）",
        "ic": "利用可"
      },
      "kumamoto": {
        "outbound": "熊本 7:45発 → JR豊肥本線特急あそ → 大分乗換 → 別府 10:20着",
        "return": "別府 17:00発 → 大分乗換 → JR豊肥本線 → 熊本 19:40着",
        "time": "約2時間30分",
        "price": "約6,800円（往復）",
        "ic": "利用可"
      }
    },
    "budgetLevel": 4,
    "region": "九州",
    "staySupport": [
      "daytrip",
      "1night"
    ],
    "transportType": "rail",
    "baseTravelHours": 2.5
  },
  {
    "id": "yufuin",
    "city": "由布院",
    "prefecture": "大分県",
    "prefectureSlug": "oita",
    "description": "由布岳の麓の温泉とアートの街",
    "themes": [
      "view",
      "experience"
    ],
    "modelCourses": [
      "金鱗湖 → 湯の坪街道散策 → 由布院温泉 → 由布岳展望",
      "由布院フローラルヴィレッジ → ステンドグラス美術館 → 金鱗湖 → 温泉"
    ],
    "access": {
      "fukuoka": {
        "outbound": "博多 8:24発 → 特急ゆふいんの森1号 → 由布院 10:36着",
        "return": "由布院 16:48発 → 特急ゆふいんの森6号 → 博多 19:08着",
        "time": "約2時間12分",
        "price": "約6,000円（往復）",
        "ic": "利用可"
      },
      "kumamoto": {
        "outbound": "熊本 7:45発 → JR豊肥本線特急あそ → 大分乗換 → 由布院 10:40着",
        "return": "由布院 16:30発 → 大分乗換 → JR豊肥本線 → 熊本 19:20着",
        "time": "約2時間50分",
        "price": "約7,000円（往復）",
        "ic": "利用可"
      }
    },
    "budgetLevel": 4,
    "region": "九州",
    "staySupport": [
      "daytrip",
      "1night"
    ],
    "transportType": "rail",
    "baseTravelHours": 2.5
  },
  {
    "id": "otaru",
    "city": "小樽",
    "prefecture": "北海道",
    "prefectureSlug": "hokkaido",
    "description": "運河とガラスとお寿司の港町",
    "themes": [
      "view",
      "food"
    ],
    "modelCourses": [
      "小樽運河散策 → 堺町通り（ガラス・オルゴール） → 小樽寿司",
      "小樽運河クルーズ → 北一硝子 → ルタオ本店 → 三角市場で海鮮丼"
    ],
    "access": {
      "sapporo": {
        "outbound": "札幌 8:00発 → JR快速エアポート → 小樽 8:32着",
        "return": "小樽 18:00発 → JR快速エアポート → 札幌 18:32着",
        "time": "約32分",
        "price": "約1,280円（往復）",
        "ic": "利用可"
      }
    },
    "budgetLevel": 1,
    "region": "北海道",
    "staySupport": [
      "daytrip",
      "1night"
    ],
    "transportType": "rail",
    "baseTravelHours": 1
  },
  {
    "id": "noboribetsu",
    "city": "登別温泉",
    "prefecture": "北海道",
    "prefectureSlug": "hokkaido",
    "description": "地獄谷と多彩な泉質の温泉郷",
    "themes": [
      "experience",
      "view"
    ],
    "modelCourses": [
      "地獄谷 → 大湯沼 → 天然足湯 → 登別温泉街散策",
      "のぼりべつクマ牧場 → 地獄谷 → 大湯沼川天然足湯 → 温泉"
    ],
    "access": {
      "sapporo": {
        "outbound": "札幌 8:00発 → 特急すずらん → 登別 9:15着 → バス → 登別温泉",
        "return": "登別温泉 → バス → 登別 17:30発 → 特急すずらん → 札幌 18:45着",
        "time": "約1時間30分（バス含む）",
        "price": "約5,500円（往復）",
        "ic": "利用可"
      }
    },
    "budgetLevel": 3,
    "region": "北海道",
    "staySupport": [
      "daytrip",
      "1night"
    ],
    "transportType": "rail",
    "baseTravelHours": 2
  },
  {
    "id": "furano",
    "city": "富良野・美瑛",
    "prefecture": "北海道",
    "prefectureSlug": "hokkaido",
    "description": "ラベンダー畑と丘の絶景パッチワーク",
    "themes": [
      "view",
      "experience"
    ],
    "modelCourses": [
      "ファーム富田（ラベンダー） → 四季彩の丘 → 青い池 → 白ひげの滝",
      "パッチワークの路 → ケンとメリーの木 → ファーム富田 → 富良野チーズ工房"
    ],
    "access": {
      "sapporo": {
        "outbound": "札幌 7:30発 → JR特急ライラック → 旭川乗換 → 富良野線 → 富良野 10:10着",
        "return": "富良野 17:00発 → 富良野線 → 旭川乗換 → 特急ライラック → 札幌 19:30着",
        "time": "約2時間40分",
        "price": "約5,500円（往復）",
        "ic": "利用可"
      }
    },
    "budgetLevel": 3,
    "region": "北海道",
    "staySupport": [
      "1night",
      "2night"
    ],
    "transportType": "rail+car",
    "baseTravelHours": 3.5
  },
  {
    "id": "hakodate",
    "city": "函館",
    "prefecture": "北海道",
    "prefectureSlug": "hokkaido",
    "description": "百万ドルの夜景と朝市の海鮮",
    "themes": [
      "view",
      "food"
    ],
    "modelCourses": [
      "函館朝市 → 金森赤レンガ倉庫 → 元町散策 → 函館山ロープウェイ（夜景）",
      "五稜郭タワー → ベイエリア → 八幡坂 → 函館山夜景"
    ],
    "access": {
      "sapporo": {
        "outbound": "札幌 7:49発 → 特急北斗 → 函館 11:28着",
        "return": "函館 17:33発 → 特急北斗 → 札幌 21:12着",
        "time": "約3時間40分",
        "price": "約9,500円（往復）",
        "ic": "利用可"
      }
    },
    "budgetLevel": 5,
    "region": "北海道",
    "staySupport": [
      "1night",
      "2night"
    ],
    "transportType": "shinkansen",
    "baseTravelHours": 4
  },
  {
    "id": "asahiyama",
    "city": "旭川（旭山動物園）",
    "prefecture": "北海道",
    "prefectureSlug": "hokkaido",
    "description": "行動展示で人気の動物園と旭川ラーメン",
    "themes": [
      "experience",
      "food"
    ],
    "modelCourses": [
      "旭山動物園（ペンギン・ホッキョクグマ） → 旭川ラーメン村",
      "旭山動物園 → 上野ファーム → 旭川ラーメン"
    ],
    "access": {
      "sapporo": {
        "outbound": "札幌 7:30発 → 特急ライラック → 旭川 8:55着 → バス → 旭山動物園",
        "return": "旭山動物園 → バス → 旭川 17:00発 → 特急ライラック → 札幌 18:25着",
        "time": "約2時間（バス含む）",
        "price": "約5,500円（往復・バス別）",
        "ic": "利用可"
      }
    },
    "budgetLevel": 3,
    "region": "北海道",
    "staySupport": [
      "1night",
      "2night"
    ],
    "transportType": "rail+car",
    "baseTravelHours": 3.5
  },
  {
    "id": "matsushima",
    "city": "松島",
    "prefecture": "宮城県",
    "prefectureSlug": "miyagi",
    "description": "日本三景の島々と瑞巌寺",
    "themes": [
      "view",
      "food"
    ],
    "modelCourses": [
      "松島湾遊覧船 → 瑞巌寺 → 五大堂 → 松島さかな市場で牡蠣",
      "福浦島 → 円通院 → 瑞巌寺 → 牡蠣小屋 → 松島海岸散策"
    ],
    "access": {
      "sendai": {
        "outbound": "仙台 8:15発 → JR仙石線 → 松島海岸 8:55着",
        "return": "松島海岸 17:30発 → JR仙石線 → 仙台 18:10着",
        "time": "約40分",
        "price": "約840円（往復）",
        "ic": "利用可"
      }
    },
    "budgetLevel": 1,
    "region": "東北",
    "staySupport": [
      "daytrip"
    ],
    "transportType": "rail",
    "baseTravelHours": 1
  },
  {
    "id": "yamadera",
    "city": "山寺（山形市）",
    "prefecture": "山形県",
    "prefectureSlug": "yamagata",
    "description": "奥の細道・1015段の石段と絶景",
    "themes": [
      "view",
      "experience"
    ],
    "modelCourses": [
      "立石寺（山寺）石段登り → 五大堂からの絶景 → 山寺芭蕉記念館 → 冷やしそば",
      "山寺 → 山形市内 → 蔵王温泉（日帰り入浴）"
    ],
    "access": {
      "sendai": {
        "outbound": "仙台 8:00発 → JR仙山線 → 山寺 8:55着",
        "return": "山寺 17:00発 → JR仙山線 → 仙台 17:55着",
        "time": "約55分",
        "price": "約1,700円（往復）",
        "ic": "利用可"
      }
    },
    "budgetLevel": 2,
    "region": "東北",
    "staySupport": [
      "daytrip"
    ],
    "transportType": "rail",
    "baseTravelHours": 1.5
  },
  {
    "id": "hiraizumi",
    "city": "平泉",
    "prefecture": "岩手県",
    "prefectureSlug": "iwate",
    "description": "世界遺産・中尊寺金色堂と浄土庭園",
    "themes": [
      "view",
      "experience"
    ],
    "modelCourses": [
      "中尊寺（金色堂） → 毛越寺 → 平泉わんこそば",
      "毛越寺（浄土庭園） → 中尊寺 → 高館義経堂 → 前沢牛ランチ"
    ],
    "access": {
      "sendai": {
        "outbound": "仙台 8:00発 → 東北新幹線 → 一ノ関 8:30着 → JR → 平泉 8:38着",
        "return": "平泉 17:30発 → JR → 一ノ関 → 東北新幹線 → 仙台 18:15着",
        "time": "約40分",
        "price": "約4,500円（往復）",
        "ic": "利用可"
      }
    },
    "budgetLevel": 3,
    "region": "東北",
    "staySupport": [
      "daytrip",
      "1night"
    ],
    "transportType": "shinkansen",
    "baseTravelHours": 2.5
  },
  {
    "id": "aizuwakamatsu",
    "city": "会津若松",
    "prefecture": "福島県",
    "prefectureSlug": "fukushima",
    "description": "鶴ヶ城と白虎隊の歴史ロマン",
    "themes": [
      "experience",
      "food"
    ],
    "modelCourses": [
      "鶴ヶ城 → 飯盛山（白虎隊） → 七日町通り散策 → ソースカツ丼",
      "大内宿 → 鶴ヶ城 → 会津ラーメン → 東山温泉"
    ],
    "access": {
      "sendai": {
        "outbound": "仙台 7:40発 → 東北新幹線 → 郡山乗換 → 磐越西線 → 会津若松 10:00着",
        "return": "会津若松 17:00発 → 磐越西線 → 郡山 → 東北新幹線 → 仙台 19:10着",
        "time": "約2時間20分",
        "price": "約6,500円（往復）",
        "ic": "利用可"
      },
      "niigata": {
        "outbound": "新潟 7:30発 → 磐越西線SLばんえつ物語or快速 → 会津若松 10:00着",
        "return": "会津若松 16:30発 → 磐越西線 → 新潟 19:00着",
        "time": "約2時間30分",
        "price": "約3,400円（往復）",
        "ic": "利用可"
      }
    },
    "budgetLevel": 3,
    "region": "東北",
    "staySupport": [
      "daytrip",
      "1night"
    ],
    "transportType": "rail",
    "baseTravelHours": 2.5
  },
  {
    "id": "echigoyuzawa",
    "city": "越後湯沢",
    "prefecture": "新潟県",
    "prefectureSlug": "niigata",
    "description": "温泉と日本酒とスキーの雪国リゾート",
    "themes": [
      "experience",
      "food"
    ],
    "modelCourses": [
      "ぽんしゅ館（日本酒試飲） → 越後湯沢温泉 → へぎそば → 湯沢高原ロープウェイ",
      "GALA湯沢 or 石打丸山スキー場 → 温泉 → 越後もち豚ランチ"
    ],
    "access": {
      "niigata": {
        "outbound": "新潟 8:30発 → 上越新幹線 → 越後湯沢 9:20着",
        "return": "越後湯沢 18:00発 → 上越新幹線 → 新潟 18:50着",
        "time": "約50分",
        "price": "約4,700円（往復・自由席）",
        "ic": "利用可"
      },
      "tokyo": {
        "outbound": "東京 8:08発 → 上越新幹線 → 越後湯沢 9:25着",
        "return": "越後湯沢 18:12発 → 上越新幹線 → 東京 19:28着",
        "time": "約1時間17分",
        "price": "約6,800円（往復・自由席）",
        "ic": "利用可"
      }
    },
    "budgetLevel": 3,
    "region": "中部",
    "staySupport": [
      "daytrip",
      "1night"
    ],
    "transportType": "shinkansen",
    "baseTravelHours": 2
  },
  {
    "id": "sado",
    "city": "佐渡島（両津）",
    "prefecture": "新潟県",
    "prefectureSlug": "niigata",
    "description": "たらい舟と金山の自然豊かな島",
    "themes": [
      "experience",
      "view"
    ],
    "modelCourses": [
      "佐渡金山 → 北沢浮遊選鉱場跡 → たらい舟体験 → 夕日",
      "トキの森公園 → たらい舟 → 宿根木（千石船の里） → 佐渡海鮮"
    ],
    "access": {
      "niigata": {
        "outbound": "新潟港 8:05発 → カーフェリー → 両津港 10:35着",
        "return": "両津港 16:00発 → カーフェリー → 新潟港 18:30着",
        "time": "約2時間30分",
        "price": "約5,000円（往復・2等）",
        "ic": "不可（窓口購入）"
      }
    },
    "budgetLevel": 3,
    "region": "中部",
    "staySupport": [
      "1night",
      "2night"
    ],
    "transportType": "rail+car",
    "baseTravelHours": 5
  },
  {
    "id": "yahiko",
    "city": "弥彦（弥彦村）",
    "prefecture": "新潟県",
    "prefectureSlug": "niigata",
    "description": "越後一宮・弥彦神社と山頂パノラマ",
    "themes": [
      "view",
      "experience"
    ],
    "modelCourses": [
      "弥彦神社 → 弥彦山ロープウェイ → 山頂パノラマタワー → 弥彦温泉",
      "弥彦神社 → 弥彦公園 → おもてなし広場（食べ歩き） → 弥彦温泉"
    ],
    "access": {
      "niigata": {
        "outbound": "新潟 8:15発 → JR弥彦線（吉田乗換） → 弥彦 9:30着",
        "return": "弥彦 17:15発 → JR弥彦線 → 新潟 18:30着",
        "time": "約1時間15分",
        "price": "約1,500円（往復）",
        "ic": "利用可"
      }
    },
    "budgetLevel": 1,
    "region": "中部",
    "staySupport": [
      "daytrip"
    ],
    "transportType": "rail",
    "baseTravelHours": 2
  },
  {
    "id": "nagaoka",
    "city": "長岡・寺泊",
    "prefecture": "新潟県",
    "prefectureSlug": "niigata",
    "description": "花火の街と魚のアメ横",
    "themes": [
      "food",
      "experience"
    ],
    "modelCourses": [
      "寺泊魚の市場通り（浜焼き） → 長岡花火ミュージアム → アオーレ長岡",
      "国営越後丘陵公園 → 寺泊で海鮮ランチ → 長岡の醸造蔵見学"
    ],
    "access": {
      "niigata": {
        "outbound": "新潟 8:00発 → 上越新幹線 → 長岡 8:25着",
        "return": "長岡 18:00発 → 上越新幹線 → 新潟 18:25着",
        "time": "約25分",
        "price": "約3,200円（往復・自由席）",
        "ic": "利用可"
      }
    },
    "budgetLevel": 2,
    "region": "中部",
    "staySupport": [
      "daytrip"
    ],
    "transportType": "shinkansen",
    "baseTravelHours": 2
  },
  {
    "id": "enoshima",
    "city": "江ノ島",
    "prefecture": "神奈川県",
    "prefectureSlug": "kanagawa",
    "description": "湘南の海と島散策・しらすグルメ",
    "themes": [
      "view",
      "food"
    ],
    "modelCourses": [
      "江ノ島シーキャンドル → 岩屋洞窟 → しらす丼ランチ → 湘南海岸散策",
      "新江ノ島水族館 → 江ノ島神社 → サムエル・コッキング苑 → 海沿いカフェ"
    ],
    "access": {
      "tokyo": {
        "outbound": "新宿 8:00発 → 小田急線 → 片瀬江ノ島 9:10着",
        "return": "片瀬江ノ島 18:00発 → 小田急線 → 新宿 19:10着",
        "time": "約1時間10分",
        "price": "約1,300円（往復）",
        "ic": "利用可"
      },
      "yokohama": {
        "outbound": "横浜 8:30発 → JR東海道線 → 藤沢乗換 → 江ノ電 → 江ノ島 9:20着",
        "return": "江ノ島 18:00発 → 江ノ電 → 藤沢 → JR → 横浜 18:50着",
        "time": "約50分",
        "price": "約1,200円（往復）",
        "ic": "利用可"
      }
    },
    "budgetLevel": 1,
    "region": "関東",
    "staySupport": [
      "daytrip"
    ],
    "transportType": "rail",
    "baseTravelHours": 1
  },
  {
    "id": "inuyama",
    "city": "犬山",
    "prefecture": "愛知県",
    "prefectureSlug": "aichi",
    "description": "国宝犬山城と城下町の食べ歩き",
    "themes": [
      "experience",
      "food"
    ],
    "modelCourses": [
      "犬山城 → 城下町食べ歩き（五平餅・田楽） → 三光稲荷神社 → 犬山温泉",
      "日本モンキーパーク → 犬山城 → 城下町散策 → からくり展示館"
    ],
    "access": {
      "nagoya": {
        "outbound": "名鉄名古屋 8:15発 → 名鉄犬山線 → 犬山 8:41着",
        "return": "犬山 18:00発 → 名鉄犬山線 → 名鉄名古屋 18:26着",
        "time": "約26分",
        "price": "約1,180円（往復）",
        "ic": "利用可"
      }
    },
    "budgetLevel": 1,
    "region": "中部",
    "staySupport": [
      "daytrip"
    ],
    "transportType": "rail",
    "baseTravelHours": 1
  },
  {
    "id": "tokoname",
    "city": "常滑（やきもの散歩道）",
    "prefecture": "愛知県",
    "prefectureSlug": "aichi",
    "description": "招き猫と焼き物の坂道散策",
    "themes": [
      "experience",
      "view"
    ],
    "modelCourses": [
      "やきもの散歩道 → とこなめ招き猫通り → 陶芸体験 → 常滑屋でランチ",
      "INAXライブミュージアム → やきもの散歩道 → 常滑焼ショッピング"
    ],
    "access": {
      "nagoya": {
        "outbound": "名鉄名古屋 8:30発 → 名鉄常滑線 → 常滑 9:08着",
        "return": "常滑 18:00発 → 名鉄常滑線 → 名鉄名古屋 18:38着",
        "time": "約38分",
        "price": "約1,300円（往復）",
        "ic": "利用可"
      }
    },
    "budgetLevel": 1,
    "region": "中部",
    "staySupport": [
      "daytrip"
    ],
    "transportType": "rail",
    "baseTravelHours": 1
  },
  {
    "id": "iseshima",
    "city": "伊勢志摩",
    "prefecture": "三重県",
    "prefectureSlug": "mie",
    "description": "お伊勢参りとおかげ横丁グルメ",
    "themes": [
      "experience",
      "food"
    ],
    "modelCourses": [
      "伊勢神宮外宮 → 内宮 → おかげ横丁（赤福・伊勢うどん） → 夫婦岩",
      "伊勢神宮内宮 → おかげ横丁 → 鳥羽水族館 → 海女小屋で海鮮"
    ],
    "access": {
      "nagoya": {
        "outbound": "近鉄名古屋 8:00発 → 近鉄特急 → 伊勢市 9:20着",
        "return": "伊勢市 17:30発 → 近鉄特急 → 近鉄名古屋 18:50着",
        "time": "約1時間20分",
        "price": "約6,200円（往復）",
        "ic": "利用可"
      },
      "osaka": {
        "outbound": "大阪難波 8:00発 → 近鉄特急 → 伊勢市 9:50着",
        "return": "伊勢市 17:30発 → 近鉄特急 → 大阪難波 19:20着",
        "time": "約1時間50分",
        "price": "約7,400円（往復）",
        "ic": "利用可"
      }
    },
    "budgetLevel": 4,
    "region": "中部",
    "staySupport": [
      "daytrip",
      "1night"
    ],
    "transportType": "rail",
    "baseTravelHours": 3
  },
  {
    "id": "gero",
    "city": "下呂温泉",
    "prefecture": "岐阜県",
    "prefectureSlug": "gifu",
    "description": "日本三名泉のとろり美肌の湯",
    "themes": [
      "experience",
      "food"
    ],
    "modelCourses": [
      "温泉寺 → 下呂温泉街散策 → 足湯めぐり → 飛騨牛ランチ → 噴泉池",
      "合掌村 → 温泉街食べ歩き → 日帰り温泉 → 飛騨牛コロッケ"
    ],
    "access": {
      "nagoya": {
        "outbound": "名古屋 7:43発 → 特急ひだ → 下呂 9:22着",
        "return": "下呂 17:33発 → 特急ひだ → 名古屋 19:09着",
        "time": "約1時間40分",
        "price": "約8,500円（往復）",
        "ic": "利用可"
      }
    },
    "budgetLevel": 4,
    "region": "中部",
    "staySupport": [
      "1night"
    ],
    "transportType": "rail",
    "baseTravelHours": 3
  },
  {
    "id": "takayama",
    "city": "高山",
    "prefecture": "岐阜県",
    "prefectureSlug": "gifu",
    "description": "飛騨の小京都・古い町並みと朝市",
    "themes": [
      "experience",
      "food"
    ],
    "modelCourses": [
      "宮川朝市 → 古い町並み散策 → 飛騨牛握り → 高山陣屋 → 飛騨の里",
      "古い町並み → 飛騨高山レトロミュージアム → 高山ラーメン → 中橋散策"
    ],
    "access": {
      "nagoya": {
        "outbound": "名古屋 7:43発 → 特急ひだ → 高山 10:07着",
        "return": "高山 17:08発 → 特急ひだ → 名古屋 19:39着",
        "time": "約2時間24分",
        "price": "約12,000円（往復）",
        "ic": "利用可"
      },
      "kanazawa": {
        "outbound": "金沢 8:00発 → 高速バス → 高山 10:15着",
        "return": "高山 17:00発 → 高速バス → 金沢 19:15着",
        "time": "約2時間15分",
        "price": "約4,000円（往復）",
        "ic": "不可（事前予約）"
      }
    },
    "budgetLevel": 4,
    "region": "中部",
    "staySupport": [
      "daytrip",
      "1night"
    ],
    "transportType": "rail",
    "baseTravelHours": 3.5
  },
  {
    "id": "shirakawago",
    "city": "白川郷",
    "prefecture": "岐阜県",
    "prefectureSlug": "gifu",
    "description": "世界遺産の合掌造り集落",
    "themes": [
      "view",
      "experience"
    ],
    "modelCourses": [
      "荻町城跡展望台 → 和田家 → 合掌造り集落散策 → 白川郷の湯",
      "であい橋 → 長瀬家 → 明善寺 → 展望台 → 飛騨牛コロッケ"
    ],
    "access": {
      "kanazawa": {
        "outbound": "金沢 8:10発 → 高速バス → 白川郷 9:25着",
        "return": "白川郷 16:30発 → 高速バス → 金沢 17:45着",
        "time": "約1時間15分",
        "price": "約3,800円（往復）",
        "ic": "不可（事前予約）"
      },
      "nagoya": {
        "outbound": "名古屋 8:00発 → 高速バス → 白川郷 10:50着",
        "return": "白川郷 15:30発 → 高速バス → 名古屋 18:20着",
        "time": "約2時間50分",
        "price": "約4,400円（往復）",
        "ic": "不可（事前予約）"
      }
    },
    "budgetLevel": 3,
    "region": "中部",
    "staySupport": [
      "daytrip",
      "1night"
    ],
    "transportType": "rail+car",
    "baseTravelHours": 4
  },
  {
    "id": "tojinbo",
    "city": "東尋坊",
    "prefecture": "福井県",
    "prefectureSlug": "fukui",
    "description": "断崖絶壁の絶景と越前ガニ",
    "themes": [
      "view",
      "food"
    ],
    "modelCourses": [
      "東尋坊（遊覧船） → 越前松島水族館 → 芝政ワールド → 越前そば",
      "東尋坊 → 丸岡城 → 永平寺 → 越前おろしそば"
    ],
    "access": {
      "kanazawa": {
        "outbound": "金沢 8:00発 → JR北陸本線 → 芦原温泉 8:40着 → バス → 東尋坊",
        "return": "東尋坊 → バス → 芦原温泉 17:30発 → JR → 金沢 18:10着",
        "time": "約1時間20分（バス含む）",
        "price": "約3,200円（往復・バス別）",
        "ic": "JR区間のみ利用可"
      }
    },
    "budgetLevel": 2,
    "region": "中部",
    "staySupport": [
      "daytrip"
    ],
    "transportType": "rail",
    "baseTravelHours": 2
  },
  {
    "id": "wakura",
    "city": "和倉温泉",
    "prefecture": "石川県",
    "prefectureSlug": "ishikawa",
    "description": "能登の海沿い名湯と海鮮グルメ",
    "themes": [
      "experience",
      "food"
    ],
    "modelCourses": [
      "総湯 → 辻口博啓美術館 → 能登島大橋 → のとじま水族館 → 海鮮ランチ",
      "和倉温泉街散策 → 足湯 → 能登食祭市場 → 七尾城跡"
    ],
    "access": {
      "kanazawa": {
        "outbound": "金沢 8:00発 → JR七尾線 → 和倉温泉 9:20着",
        "return": "和倉温泉 17:30発 → JR七尾線 → 金沢 18:50着",
        "time": "約1時間20分",
        "price": "約2,600円（往復）",
        "ic": "利用可"
      }
    },
    "budgetLevel": 2,
    "region": "中部",
    "staySupport": [
      "1night"
    ],
    "transportType": "rail",
    "baseTravelHours": 3
  },
  {
    "id": "uji",
    "city": "宇治",
    "prefecture": "京都府",
    "prefectureSlug": "kyoto",
    "description": "平等院鳳凰堂と宇治抹茶の街",
    "themes": [
      "view",
      "food"
    ],
    "modelCourses": [
      "平等院鳳凰堂 → 宇治上神社 → 宇治抹茶スイーツ → 中村藤吉本店",
      "平等院 → 源氏物語ミュージアム → 宇治川沿い散策 → 抹茶ソフト"
    ],
    "access": {
      "kyoto": {
        "outbound": "京都 8:30発 → JR奈良線 → 宇治 8:47着",
        "return": "宇治 18:00発 → JR奈良線 → 京都 18:17着",
        "time": "約17分",
        "price": "約480円（往復）",
        "ic": "利用可"
      },
      "osaka": {
        "outbound": "大阪 8:15発 → JR → 京都乗換 → JR奈良線 → 宇治 9:10着",
        "return": "宇治 18:00発 → JR奈良線 → 京都 → JR → 大阪 18:55着",
        "time": "約55分",
        "price": "約1,600円（往復）",
        "ic": "利用可"
      }
    },
    "budgetLevel": 1,
    "region": "近畿",
    "staySupport": [
      "daytrip"
    ],
    "transportType": "rail",
    "baseTravelHours": 1
  },
  {
    "id": "amanohashidate",
    "city": "天橋立",
    "prefecture": "京都府",
    "prefectureSlug": "kyoto",
    "description": "日本三景・股のぞきの絶景",
    "themes": [
      "view",
      "experience"
    ],
    "modelCourses": [
      "天橋立ビューランド（股のぞき） → 松並木散策 → 智恩寺 → 海鮮ランチ",
      "傘松公園リフト → 成相寺 → 天橋立松並木レンタサイクル → 廻旋橋"
    ],
    "access": {
      "kyoto": {
        "outbound": "京都 8:25発 → 特急はしだて → 天橋立 10:30着",
        "return": "天橋立 17:15発 → 特急はしだて → 京都 19:19着",
        "time": "約2時間5分",
        "price": "約5,400円（往復）",
        "ic": "JR区間のみ利用可"
      },
      "osaka": {
        "outbound": "大阪 8:00発 → JR → 福知山乗換 → 京都丹後鉄道 → 天橋立 10:30着",
        "return": "天橋立 17:00発 → 京都丹後鉄道 → 福知山 → JR → 大阪 19:30着",
        "time": "約2時間30分",
        "price": "約6,000円（往復）",
        "ic": "JR区間のみ利用可"
      }
    },
    "budgetLevel": 3,
    "region": "近畿",
    "staySupport": [
      "daytrip",
      "1night"
    ],
    "transportType": "rail",
    "baseTravelHours": 3.5
  },
  {
    "id": "kinosaki",
    "city": "城崎温泉",
    "prefecture": "兵庫県",
    "prefectureSlug": "hyogo",
    "description": "七つの外湯めぐりと但馬の味覚",
    "themes": [
      "experience",
      "food"
    ],
    "modelCourses": [
      "外湯めぐり（御所の湯・一の湯） → 城崎ロープウェイ → 温泉街散策 → カニ料理",
      "城崎マリンワールド → 外湯めぐり → 温泉街食べ歩き → 但馬牛"
    ],
    "access": {
      "kyoto": {
        "outbound": "京都 8:37発 → 特急きのさき → 城崎温泉 11:12着",
        "return": "城崎温泉 17:01発 → 特急きのさき → 京都 19:32着",
        "time": "約2時間35分",
        "price": "約6,000円（往復）",
        "ic": "利用可"
      },
      "osaka": {
        "outbound": "大阪 8:11発 → 特急こうのとり → 城崎温泉 10:52着",
        "return": "城崎温泉 17:01発 → 特急こうのとり → 大阪 19:40着",
        "time": "約2時間40分",
        "price": "約6,000円（往復）",
        "ic": "利用可"
      },
      "kobe": {
        "outbound": "三ノ宮 8:00発 → JR → 大阪乗換 → 特急こうのとり → 城崎温泉 10:52着",
        "return": "城崎温泉 17:01発 → 特急こうのとり → 大阪 → JR → 三ノ宮 19:55着",
        "time": "約2時間50分",
        "price": "約6,500円（往復）",
        "ic": "利用可"
      }
    },
    "budgetLevel": 4,
    "region": "近畿",
    "staySupport": [
      "1night"
    ],
    "transportType": "rail",
    "baseTravelHours": 3.5
  },
  {
    "id": "awajishima",
    "city": "淡路島",
    "prefecture": "兵庫県",
    "prefectureSlug": "hyogo",
    "description": "花と海と淡路島バーガーの島",
    "themes": [
      "view",
      "food"
    ],
    "modelCourses": [
      "あわじ花さじき → 淡路島バーガー → 淡路ワールドパークONOKORO → 明石海峡大橋展望",
      "淡路夢舞台 → 国営明石海峡公園 → 生しらす丼 → うずしおクルーズ"
    ],
    "access": {
      "kobe": {
        "outbound": "三ノ宮BT 8:30発 → 高速バス → 淡路IC 9:15着",
        "return": "淡路IC 17:30発 → 高速バス → 三ノ宮BT 18:15着",
        "time": "約45分",
        "price": "約1,850円（往復）",
        "ic": "不可（窓口 or 事前購入）"
      },
      "osaka": {
        "outbound": "大阪 8:30発 → 高速バス → 淡路IC 10:00着",
        "return": "淡路IC 17:00発 → 高速バス → 大阪 18:30着",
        "time": "約1時間30分",
        "price": "約3,100円（往復）",
        "ic": "不可（事前購入）"
      }
    },
    "budgetLevel": 2,
    "region": "近畿",
    "staySupport": [
      "daytrip",
      "1night"
    ],
    "transportType": "rail+car",
    "baseTravelHours": 2.5
  },
  {
    "id": "tottori",
    "city": "鳥取砂丘",
    "prefecture": "鳥取県",
    "prefectureSlug": "tottori",
    "description": "日本最大級の砂丘とらくだ体験",
    "themes": [
      "view",
      "experience"
    ],
    "modelCourses": [
      "鳥取砂丘 → らくだ体験 → 砂の美術館 → 白兎神社 → 海鮮ランチ",
      "鳥取砂丘パラグライダー → 砂の美術館 → 鳥取市内でカニ料理"
    ],
    "access": {
      "matsue": {
        "outbound": "松江 8:00発 → 特急スーパーまつかぜ → 鳥取 9:50着 → バス → 砂丘",
        "return": "砂丘 → バス → 鳥取 17:00発 → 特急スーパーまつかぜ → 松江 18:50着",
        "time": "約2時間10分（バス含む）",
        "price": "約4,500円（往復・バス別）",
        "ic": "JR区間のみ利用可"
      },
      "kobe": {
        "outbound": "三ノ宮 8:00発 → 高速バス → 鳥取 10:40着 → バス → 砂丘",
        "return": "砂丘 → バス → 鳥取 16:30発 → 高速バス → 三ノ宮 19:10着",
        "time": "約3時間（バス含む）",
        "price": "約3,800円（往復・バス別）",
        "ic": "不可（事前予約）"
      }
    },
    "budgetLevel": 3,
    "region": "中国",
    "staySupport": [
      "daytrip",
      "1night"
    ],
    "transportType": "rail",
    "baseTravelHours": 3
  },
  {
    "id": "miyajima",
    "city": "宮島（廿日市市）",
    "prefecture": "広島県",
    "prefectureSlug": "hiroshima",
    "description": "海に浮かぶ朱色の大鳥居と厳島神社",
    "themes": [
      "view",
      "experience"
    ],
    "modelCourses": [
      "厳島神社 → 大鳥居 → 表参道商店街（もみじ饅頭・穴子飯） → 弥山ロープウェイ",
      "弥山登山 → 厳島神社 → 五重塔 → 表参道で牡蠣 → 大鳥居ライトアップ"
    ],
    "access": {
      "hiroshima": {
        "outbound": "広島 8:15発 → JR山陽本線 → 宮島口 8:43着 → フェリー → 宮島 8:53着",
        "return": "宮島 18:00発 → フェリー → 宮島口 → JR → 広島 18:40着",
        "time": "約40分（フェリー含む）",
        "price": "約1,000円（往復・フェリー込み）",
        "ic": "利用可"
      },
      "okayama": {
        "outbound": "岡山 8:08発 → 新幹線 → 広島 → JR → 宮島口 → フェリー → 宮島 9:40着",
        "return": "宮島 17:30発 → フェリー → 宮島口 → JR → 広島 → 新幹線 → 岡山 19:10着",
        "time": "約1時間30分",
        "price": "約8,000円（往復）",
        "ic": "利用可"
      }
    },
    "budgetLevel": 3,
    "region": "中国",
    "staySupport": [
      "daytrip"
    ],
    "transportType": "rail",
    "baseTravelHours": 2.5
  },
  {
    "id": "kure",
    "city": "呉",
    "prefecture": "広島県",
    "prefectureSlug": "hiroshima",
    "description": "大和ミュージアムと海軍カレーの港町",
    "themes": [
      "experience",
      "food"
    ],
    "modelCourses": [
      "大和ミュージアム → てつのくじら館 → 海軍カレーランチ → 呉港クルーズ",
      "アレイからすこじま → 海軍カレー → 大和ミュージアム → 音戸の瀬戸"
    ],
    "access": {
      "hiroshima": {
        "outbound": "広島 8:20発 → JR呉線 → 呉 9:00着",
        "return": "呉 18:00発 → JR呉線 → 広島 18:40着",
        "time": "約40分",
        "price": "約1,000円（往復）",
        "ic": "利用可"
      }
    },
    "budgetLevel": 1,
    "region": "中国",
    "staySupport": [
      "daytrip"
    ],
    "transportType": "rail",
    "baseTravelHours": 1.5
  },
  {
    "id": "iwakuni",
    "city": "岩国（錦帯橋）",
    "prefecture": "山口県",
    "prefectureSlug": "yamaguchi",
    "description": "日本三名橋・錦帯橋と岩国寿司",
    "themes": [
      "view",
      "food"
    ],
    "modelCourses": [
      "錦帯橋 → 吉香公園 → 岩国城ロープウェイ → 岩国寿司ランチ",
      "錦帯橋 → 白蛇の館 → 岩国城 → 岩国シロヘビの館 → 地酒試飲"
    ],
    "access": {
      "hiroshima": {
        "outbound": "広島 8:00発 → JR山陽本線 → 岩国 8:50着",
        "return": "岩国 18:00発 → JR山陽本線 → 広島 18:50着",
        "time": "約50分",
        "price": "約1,600円（往復）",
        "ic": "利用可"
      }
    },
    "budgetLevel": 2,
    "region": "中国",
    "staySupport": [
      "daytrip"
    ],
    "transportType": "rail",
    "baseTravelHours": 2
  },
  {
    "id": "izumo",
    "city": "出雲大社",
    "prefecture": "島根県",
    "prefectureSlug": "shimane",
    "description": "縁結びの聖地・出雲大社と出雲そば",
    "themes": [
      "experience",
      "food"
    ],
    "modelCourses": [
      "出雲大社 → 神門通り（出雲そば・ぜんざい） → 稲佐の浜 → 島根ワイナリー",
      "出雲大社 → 古代出雲歴史博物館 → 出雲そば → 日御碕灯台"
    ],
    "access": {
      "matsue": {
        "outbound": "松江 8:00発 → 一畑電車 → 出雲大社前 9:00着",
        "return": "出雲大社前 17:30発 → 一畑電車 → 松江 18:30着",
        "time": "約1時間",
        "price": "約1,600円（往復）",
        "ic": "不可（現金のみ）"
      },
      "hiroshima": {
        "outbound": "広島 7:15発 → 高速バス → 出雲市 10:50着 → 一畑電車 → 出雲大社前",
        "return": "出雲市 16:50発 → 高速バス → 広島 20:20着",
        "time": "約3時間40分",
        "price": "約7,000円（往復）",
        "ic": "不可（事前予約）"
      }
    },
    "budgetLevel": 3,
    "region": "中国",
    "staySupport": [
      "daytrip",
      "1night"
    ],
    "transportType": "rail",
    "baseTravelHours": 3.5
  },
  {
    "id": "sakaiminato",
    "city": "境港（水木しげるロード）",
    "prefecture": "鳥取県",
    "prefectureSlug": "tottori",
    "description": "ゲゲゲの鬼太郎ロードと海鮮",
    "themes": [
      "experience",
      "food"
    ],
    "modelCourses": [
      "水木しげるロード → 水木しげる記念館 → 境港さかなセンター → 海鮮丼",
      "水木しげるロード → 妖怪神社 → 境港水産物直売センター → カニ料理"
    ],
    "access": {
      "matsue": {
        "outbound": "松江 8:30発 → JR境線 → 境港 9:15着",
        "return": "境港 17:30発 → JR境線 → 松江 18:15着",
        "time": "約45分",
        "price": "約1,200円（往復）",
        "ic": "利用可"
      }
    },
    "budgetLevel": 1,
    "region": "中国",
    "staySupport": [
      "daytrip",
      "1night"
    ],
    "transportType": "rail",
    "baseTravelHours": 3.5
  },
  {
    "id": "yasugi",
    "city": "安来（足立美術館）",
    "prefecture": "島根県",
    "prefectureSlug": "shimane",
    "description": "日本一の庭園と横山大観コレクション",
    "themes": [
      "view",
      "experience"
    ],
    "modelCourses": [
      "足立美術館（日本庭園・横山大観） → 安来節演芸館（どじょうすくい） → 月山富田城跡",
      "足立美術館 → 清水寺（安来市） → 安来節演芸館 → しじみ料理"
    ],
    "access": {
      "matsue": {
        "outbound": "松江 8:15発 → JR山陰本線 → 安来 8:40着 → 無料シャトルバス → 足立美術館",
        "return": "足立美術館 → シャトルバス → 安来 17:10発 → JR → 松江 17:35着",
        "time": "約40分（バス含む）",
        "price": "約640円（往復・バス無料）",
        "ic": "利用可"
      }
    },
    "budgetLevel": 1,
    "region": "中国",
    "staySupport": [
      "daytrip"
    ],
    "transportType": "rail",
    "baseTravelHours": 3
  },
  {
    "id": "imabari",
    "city": "今治（しまなみ海道）",
    "prefecture": "愛媛県",
    "prefectureSlug": "ehime",
    "description": "しまなみ海道サイクリングと来島海峡",
    "themes": [
      "view",
      "experience"
    ],
    "modelCourses": [
      "サンライズ糸山 → しまなみ海道サイクリング → 大島 → 来島海峡大橋 → 焼豚玉子飯",
      "来島海峡急流観潮船 → 亀老山展望公園 → 今治城 → 焼き鳥ランチ"
    ],
    "access": {
      "matsuyama": {
        "outbound": "松山 8:15発 → JR予讃線特急 → 今治 8:52着",
        "return": "今治 18:00発 → JR予讃線特急 → 松山 18:37着",
        "time": "約37分",
        "price": "約2,500円（往復）",
        "ic": "利用可"
      },
      "hiroshima": {
        "outbound": "広島 8:00発 → 高速バス（しまなみライナー） → 今治 10:20着",
        "return": "今治 17:00発 → 高速バス → 広島 19:20着",
        "time": "約2時間20分",
        "price": "約4,600円（往復）",
        "ic": "不可（事前予約）"
      }
    },
    "budgetLevel": 3,
    "region": "四国",
    "staySupport": [
      "daytrip"
    ],
    "transportType": "rail",
    "baseTravelHours": 2.5
  },
  {
    "id": "uchiko",
    "city": "内子",
    "prefecture": "愛媛県",
    "prefectureSlug": "ehime",
    "description": "白壁の町並みと内子座の歴史ロマン",
    "themes": [
      "view",
      "experience"
    ],
    "modelCourses": [
      "内子座（芝居小屋） → 八日市・護国の町並み → 木蝋資料館上芳我邸 → 内子豚ランチ",
      "町並み散策 → 商いと暮らし博物館 → 内子フレッシュパークからり → 大洲城"
    ],
    "access": {
      "matsuyama": {
        "outbound": "松山 8:20発 → JR特急宇和海 → 内子 8:45着",
        "return": "内子 17:30発 → JR特急宇和海 → 松山 17:55着",
        "time": "約25分",
        "price": "約2,600円（往復）",
        "ic": "利用可"
      }
    },
    "budgetLevel": 2,
    "region": "四国",
    "staySupport": [
      "daytrip"
    ],
    "transportType": "rail",
    "baseTravelHours": 3
  },
  {
    "id": "ozu",
    "city": "大洲",
    "prefecture": "愛媛県",
    "prefectureSlug": "ehime",
    "description": "伊予の小京都と肱川の城下町",
    "themes": [
      "view",
      "food"
    ],
    "modelCourses": [
      "大洲城 → おはなはん通り → 臥龍山荘 → 肱川沿い散策 → 大洲コロッケ",
      "ポコペン横丁 → 大洲城 → 臥龍山荘 → 鵜飼い（夏季）"
    ],
    "access": {
      "matsuyama": {
        "outbound": "松山 8:20発 → JR特急宇和海 → 伊予大洲 9:00着",
        "return": "伊予大洲 17:45発 → JR特急宇和海 → 松山 18:25着",
        "time": "約40分",
        "price": "約2,900円（往復）",
        "ic": "利用可"
      }
    },
    "budgetLevel": 2,
    "region": "四国",
    "staySupport": [
      "daytrip"
    ],
    "transportType": "rail",
    "baseTravelHours": 3
  },
  {
    "id": "shimanto",
    "city": "四万十（四万十市）",
    "prefecture": "高知県",
    "prefectureSlug": "kochi",
    "description": "日本最後の清流と沈下橋",
    "themes": [
      "view",
      "experience"
    ],
    "modelCourses": [
      "佐田沈下橋 → 四万十川カヌー体験 → 四万十の天然うなぎランチ",
      "四万十川遊覧船 → 岩間沈下橋 → 安並水車の里 → 四万十うなぎ"
    ],
    "access": {
      "kochi": {
        "outbound": "高知 7:58発 → 特急あしずり → 中村 9:40着",
        "return": "中村 17:00発 → 特急あしずり → 高知 18:42着",
        "time": "約1時間42分",
        "price": "約5,200円（往復）",
        "ic": "利用可"
      }
    },
    "budgetLevel": 3,
    "region": "四国",
    "staySupport": [
      "1night"
    ],
    "transportType": "rail",
    "baseTravelHours": 4.5
  },
  {
    "id": "muroto",
    "city": "室戸岬",
    "prefecture": "高知県",
    "prefectureSlug": "kochi",
    "description": "世界ジオパークの断崖と深海",
    "themes": [
      "view",
      "experience"
    ],
    "modelCourses": [
      "室戸岬灯台 → 中岡慎太郎像 → 室戸世界ジオパークセンター → 室戸海洋深層水アクア・ファーム",
      "御厨人窟 → 最御崎寺 → 室戸ドルフィンセンター → キンメ丼ランチ"
    ],
    "access": {
      "kochi": {
        "outbound": "高知 7:30発 → 高知東部交通バス → 室戸岬 10:10着",
        "return": "室戸岬 16:00発 → 高知東部交通バス → 高知 18:40着",
        "time": "約2時間40分",
        "price": "約3,200円（往復）",
        "ic": "不可（現金のみ）"
      }
    },
    "budgetLevel": 2,
    "region": "四国",
    "staySupport": [
      "1night"
    ],
    "transportType": "rail+car",
    "baseTravelHours": 4.5
  },
  {
    "id": "niyodogawa",
    "city": "仁淀川（いの町）",
    "prefecture": "高知県",
    "prefectureSlug": "kochi",
    "description": "仁淀ブルーの奇跡の清流",
    "themes": [
      "view",
      "experience"
    ],
    "modelCourses": [
      "にこ淵 → 安居渓谷（水晶淵） → 仁淀川カヌー体験",
      "中津渓谷 → にこ淵 → 仁淀川沿いドライブ → 土佐和紙工芸村"
    ],
    "access": {
      "kochi": {
        "outbound": "高知 8:30発 → JR → 伊野 → バス → にこ淵 10:00着",
        "return": "にこ淵 16:00発 → バス → 伊野 → JR → 高知 17:30着",
        "time": "約1時間30分（バス含む）",
        "price": "約2,000円（往復・バス別）",
        "ic": "JR区間のみ利用可"
      }
    },
    "budgetLevel": 2,
    "region": "四国",
    "staySupport": [
      "daytrip",
      "1night"
    ],
    "transportType": "rail+car",
    "baseTravelHours": 3.5
  },
  {
    "id": "aso",
    "city": "阿蘇",
    "prefecture": "熊本県",
    "prefectureSlug": "kumamoto",
    "description": "世界最大級のカルデラと草千里",
    "themes": [
      "view",
      "experience"
    ],
    "modelCourses": [
      "阿蘇山火口 → 草千里ヶ浜 → 阿蘇神社 → あか牛丼ランチ",
      "大観峰 → 草千里 → 阿蘇中岳火口 → 内牧温泉"
    ],
    "access": {
      "kumamoto": {
        "outbound": "熊本 8:00発 → JR豊肥本線特急あそ → 阿蘇 9:15着",
        "return": "阿蘇 17:30発 → JR豊肥本線 → 熊本 18:55着",
        "time": "約1時間15分",
        "price": "約2,800円（往復）",
        "ic": "利用可"
      },
      "fukuoka": {
        "outbound": "博多 8:00発 → 九州新幹線 → 熊本乗換 → JR特急あそ → 阿蘇 10:15着",
        "return": "阿蘇 17:00発 → JR → 熊本 → 九州新幹線 → 博多 19:15着",
        "time": "約2時間15分",
        "price": "約7,500円（往復）",
        "ic": "利用可"
      },
      "kagoshima": {
        "outbound": "鹿児島中央 7:30発 → 九州新幹線 → 熊本乗換 → JR特急あそ → 阿蘇 10:15着",
        "return": "阿蘇 17:00発 → JR → 熊本 → 九州新幹線 → 鹿児島中央 19:30着",
        "time": "約2時間45分",
        "price": "約9,000円（往復）",
        "ic": "利用可"
      }
    },
    "budgetLevel": 4,
    "region": "九州",
    "staySupport": [
      "daytrip",
      "1night"
    ],
    "transportType": "rail+car",
    "baseTravelHours": 3
  },
  {
    "id": "nagasaki",
    "city": "長崎",
    "prefecture": "長崎県",
    "prefectureSlug": "nagasaki",
    "description": "異国情緒あふれる坂の街とちゃんぽん",
    "themes": [
      "experience",
      "food"
    ],
    "modelCourses": [
      "グラバー園 → 大浦天主堂 → 中華街（ちゃんぽん） → 稲佐山夜景",
      "平和公園 → 原爆資料館 → 出島 → 眼鏡橋 → トルコライス"
    ],
    "access": {
      "fukuoka": {
        "outbound": "博多 8:15発 → 西九州新幹線かもめ → 長崎 9:37着",
        "return": "長崎 18:00発 → 西九州新幹線かもめ → 博多 19:22着",
        "time": "約1時間22分",
        "price": "約6,000円（往復・自由席）",
        "ic": "利用可"
      },
      "kumamoto": {
        "outbound": "熊本 7:30発 → 九州新幹線 → 新鳥栖乗換 → 西九州新幹線 → 長崎 9:30着",
        "return": "長崎 17:30発 → 西九州新幹線 → 新鳥栖 → 九州新幹線 → 熊本 19:30着",
        "time": "約2時間",
        "price": "約8,500円（往復）",
        "ic": "利用可"
      }
    },
    "budgetLevel": 4,
    "region": "九州",
    "staySupport": [
      "daytrip",
      "1night"
    ],
    "transportType": "shinkansen",
    "baseTravelHours": 2.5
  },
  {
    "id": "amakusa",
    "city": "天草",
    "prefecture": "熊本県",
    "prefectureSlug": "kumamoto",
    "description": "世界遺産の潜伏キリシタンとイルカウォッチング",
    "themes": [
      "experience",
      "view"
    ],
    "modelCourses": [
      "天草五橋ドライブ → 崎津集落（世界遺産） → イルカウォッチング",
      "天草キリシタン館 → 崎津天主堂 → 大江天主堂 → 海鮮ランチ"
    ],
    "access": {
      "kumamoto": {
        "outbound": "熊本 8:00発 → 快速バスあまくさ号 → 本渡BT 10:20着",
        "return": "本渡BT 16:30発 → 快速バス → 熊本 18:50着",
        "time": "約2時間20分",
        "price": "約3,800円（往復）",
        "ic": "不可（現金 or 回数券）"
      }
    },
    "budgetLevel": 3,
    "region": "九州",
    "staySupport": [
      "1night"
    ],
    "transportType": "rail+car",
    "baseTravelHours": 4
  },
  {
    "id": "hitoyoshi",
    "city": "人吉",
    "prefecture": "熊本県",
    "prefectureSlug": "kumamoto",
    "description": "球磨焼酎と相良700年の城下町",
    "themes": [
      "food",
      "experience"
    ],
    "modelCourses": [
      "人吉城跡 → 球磨焼酎蔵めぐり → 鍛冶屋町通り → うなぎランチ",
      "青井阿蘇神社（国宝） → 人吉城跡 → 焼酎試飲 → 球磨川ラフティング"
    ],
    "access": {
      "kumamoto": {
        "outbound": "熊本 8:30発 → 高速バス → 人吉IC 10:00着",
        "return": "人吉IC 17:00発 → 高速バス → 熊本 18:30着",
        "time": "約1時間30分",
        "price": "約3,600円（往復）",
        "ic": "不可（事前購入）"
      }
    },
    "budgetLevel": 3,
    "region": "九州",
    "staySupport": [
      "daytrip",
      "1night"
    ],
    "transportType": "rail",
    "baseTravelHours": 3
  },
  {
    "id": "sakurajima",
    "city": "桜島",
    "prefecture": "鹿児島県",
    "prefectureSlug": "kagoshima",
    "description": "活火山の迫力と溶岩の絶景",
    "themes": [
      "view",
      "experience"
    ],
    "modelCourses": [
      "桜島フェリー → 湯之平展望所 → 有村溶岩展望所 → 桜島溶岩なぎさ足湯",
      "桜島ビジターセンター → 烏島展望所 → 叫びの肖像 → 溶岩なぎさ遊歩道"
    ],
    "access": {
      "kagoshima": {
        "outbound": "鹿児島港 8:30発 → 桜島フェリー → 桜島港 8:45着",
        "return": "桜島港 17:30発 → 桜島フェリー → 鹿児島港 17:45着",
        "time": "約15分",
        "price": "約400円（往復）",
        "ic": "利用可"
      }
    },
    "budgetLevel": 1,
    "region": "九州",
    "staySupport": [
      "daytrip"
    ],
    "transportType": "rail",
    "baseTravelHours": 2.5
  },
  {
    "id": "ibusuki",
    "city": "指宿",
    "prefecture": "鹿児島県",
    "prefectureSlug": "kagoshima",
    "description": "砂むし温泉と開聞岳の絶景",
    "themes": [
      "experience",
      "view"
    ],
    "modelCourses": [
      "砂むし会館砂楽 → 長崎鼻（開聞岳ビュー） → たまて箱温泉 → 池田湖",
      "JR特急指宿のたまて箱 → 砂むし温泉 → 知林ヶ島 → そうめん流し"
    ],
    "access": {
      "kagoshima": {
        "outbound": "鹿児島中央 8:56発 → 特急指宿のたまて箱 → 指宿 9:47着",
        "return": "指宿 17:56発 → 特急指宿のたまて箱 → 鹿児島中央 18:47着",
        "time": "約51分",
        "price": "約2,400円（往復）",
        "ic": "利用可"
      }
    },
    "budgetLevel": 2,
    "region": "九州",
    "staySupport": [
      "daytrip",
      "1night"
    ],
    "transportType": "rail",
    "baseTravelHours": 3
  },
  {
    "id": "kirishima",
    "city": "霧島",
    "prefecture": "鹿児島県",
    "prefectureSlug": "kagoshima",
    "description": "天孫降臨の神話と霧島温泉郷",
    "themes": [
      "view",
      "experience"
    ],
    "modelCourses": [
      "霧島神宮 → 丸尾滝 → 霧島温泉郷（日帰り入浴） → 高千穂牧場",
      "えびの高原 → 大浪池トレッキング → 霧島温泉 → 黒豚ランチ"
    ],
    "access": {
      "kagoshima": {
        "outbound": "鹿児島中央 8:15発 → JR日豊本線 → 霧島神宮 9:30着",
        "return": "霧島神宮 17:30発 → JR日豊本線 → 鹿児島中央 18:45着",
        "time": "約1時間15分",
        "price": "約2,500円（往復）",
        "ic": "利用可"
      },
      "kumamoto": {
        "outbound": "熊本 8:00発 → 九州新幹線 → 鹿児島中央乗換 → JR → 霧島神宮 10:30着",
        "return": "霧島神宮 17:00発 → JR → 鹿児島中央 → 九州新幹線 → 熊本 19:20着",
        "time": "約2時間30分",
        "price": "約8,500円（往復）",
        "ic": "利用可"
      }
    },
    "budgetLevel": 3,
    "region": "九州",
    "staySupport": [
      "daytrip",
      "1night"
    ],
    "transportType": "rail+car",
    "baseTravelHours": 2.5
  },
  {
    "id": "yakushima",
    "city": "屋久島",
    "prefecture": "鹿児島県",
    "prefectureSlug": "kagoshima",
    "description": "世界遺産の太古の森と縄文杉",
    "themes": [
      "view",
      "experience"
    ],
    "modelCourses": [
      "白谷雲水峡（もののけの森） → 大川の滝 → 平内海中温泉",
      "縄文杉トレッキング（往復10時間） → 屋久島温泉"
    ],
    "access": {
      "kagoshima": {
        "outbound": "鹿児島港 7:45発 → 高速船トッピー → 宮之浦港 9:45着",
        "return": "宮之浦港 16:00発 → 高速船トッピー → 鹿児島港 18:00着",
        "time": "約2時間",
        "price": "約10,800円（往復）",
        "ic": "不可（事前予約）"
      }
    },
    "budgetLevel": 5,
    "region": "九州",
    "staySupport": [
      "2night"
    ],
    "transportType": "air",
    "baseTravelHours": 6
  },
  {
    "id": "chiran",
    "city": "知覧",
    "prefecture": "鹿児島県",
    "prefectureSlug": "kagoshima",
    "description": "武家屋敷庭園と特攻平和会館",
    "themes": [
      "experience",
      "view"
    ],
    "modelCourses": [
      "知覧特攻平和会館 → 武家屋敷庭園群 → 知覧茶スイーツ",
      "武家屋敷通り → 知覧特攻平和会館 → 薩摩の里 → 知覧鶏飯ランチ"
    ],
    "access": {
      "kagoshima": {
        "outbound": "鹿児島中央 8:30発 → バス → 知覧 9:40着",
        "return": "知覧 17:00発 → バス → 鹿児島中央 18:10着",
        "time": "約1時間10分",
        "price": "約1,600円（往復）",
        "ic": "不可（現金のみ）"
      }
    },
    "budgetLevel": 2,
    "region": "九州",
    "staySupport": [
      "daytrip"
    ],
    "transportType": "rail+car",
    "baseTravelHours": 2.5
  },
  {
    "id": "churaumi",
    "city": "美ら海（本部町）",
    "prefecture": "沖縄県",
    "prefectureSlug": "okinawa",
    "description": "世界最大級の水槽とエメラルドの海",
    "themes": [
      "experience",
      "view"
    ],
    "modelCourses": [
      "美ら海水族館 → エメラルドビーチ → 備瀬のフクギ並木 → 古宇利大橋",
      "美ら海水族館 → 今帰仁城跡（世界遺産） → 古宇利島ハートロック"
    ],
    "access": {
      "naha": {
        "outbound": "那覇BT 8:00発 → 高速バス117番 → 美ら海水族館 10:30着",
        "return": "美ら海水族館 16:00発 → 高速バス → 那覇BT 18:30着",
        "time": "約2時間30分",
        "price": "約4,000円（往復）",
        "ic": "不可（現金のみ）"
      }
    },
    "budgetLevel": 3,
    "region": "九州",
    "staySupport": [
      "1night",
      "2night"
    ],
    "transportType": "air",
    "baseTravelHours": 4
  },
  {
    "id": "chatan",
    "city": "北谷（アメリカンビレッジ）",
    "prefecture": "沖縄県",
    "prefectureSlug": "okinawa",
    "description": "異国感あふれるシーサイドタウン",
    "themes": [
      "food",
      "experience"
    ],
    "modelCourses": [
      "アメリカンビレッジ → デポアイランド → サンセットビーチ → ステーキディナー",
      "アラハビーチ → アメリカンビレッジ → タコライス&ハンバーガー → 観覧車"
    ],
    "access": {
      "naha": {
        "outbound": "那覇BT 9:00発 → 路線バス28番 → 北谷 9:50着",
        "return": "北谷 18:00発 → 路線バス → 那覇BT 18:50着",
        "time": "約50分",
        "price": "約1,200円（往復）",
        "ic": "不可（現金のみ）"
      }
    },
    "budgetLevel": 1,
    "region": "九州",
    "staySupport": [
      "daytrip",
      "1night"
    ],
    "transportType": "air",
    "baseTravelHours": 2.5
  },
  {
    "id": "nanjo",
    "city": "南城（斎場御嶽）",
    "prefecture": "沖縄県",
    "prefectureSlug": "okinawa",
    "description": "琉球最高の聖地と絶景カフェ",
    "themes": [
      "experience",
      "view"
    ],
    "modelCourses": [
      "斎場御嶽（世界遺産） → 知念岬公園 → カフェくるくま（絶景ランチ） → ニライカナイ橋",
      "おきなわワールド（玉泉洞） → 斎場御嶽 → 新原ビーチ → グラスボート"
    ],
    "access": {
      "naha": {
        "outbound": "那覇BT 8:30発 → 路線バス38番 → 斎場御嶽入口 9:40着",
        "return": "斎場御嶽入口 17:00発 → 路線バス → 那覇BT 18:10着",
        "time": "約1時間10分",
        "price": "約1,400円（往復）",
        "ic": "不可（現金のみ）"
      }
    },
    "budgetLevel": 1,
    "region": "九州",
    "staySupport": [
      "daytrip",
      "1night"
    ],
    "transportType": "air",
    "baseTravelHours": 2.5
  },
  {
    "id": "yomitan",
    "city": "読谷（やちむんの里）",
    "prefecture": "沖縄県",
    "prefectureSlug": "okinawa",
    "description": "焼き物の里と沖縄の原風景",
    "themes": [
      "experience",
      "view"
    ],
    "modelCourses": [
      "やちむんの里（陶芸工房めぐり） → 座喜味城跡（世界遺産） → 残波岬 → 沖縄そば",
      "体験王国むら咲むら → やちむんの里 → 座喜味城跡 → 御菓子御殿"
    ],
    "access": {
      "naha": {
        "outbound": "那覇BT 8:15発 → 路線バス28番 → 読谷 9:30着",
        "return": "読谷 17:30発 → 路線バス → 那覇BT 18:45着",
        "time": "約1時間15分",
        "price": "約1,500円（往復）",
        "ic": "不可（現金のみ）"
      }
    },
    "budgetLevel": 1,
    "region": "九州",
    "staySupport": [
      "1night",
      "2night"
    ],
    "transportType": "air",
    "baseTravelHours": 3
  },
  {
    "id": "kouri",
    "city": "古宇利島",
    "prefecture": "沖縄県",
    "prefectureSlug": "okinawa",
    "description": "恋の島とエメラルドグリーンの海",
    "themes": [
      "view",
      "food"
    ],
    "modelCourses": [
      "古宇利大橋 → ティーヌ浜（ハートロック） → 古宇利オーシャンタワー → 海鮮ランチ",
      "古宇利ビーチ → トケイ浜 → 古宇利オーシャンタワー → ウニ丼"
    ],
    "access": {
      "naha": {
        "outbound": "那覇 8:00発 → 高速道路経由バス（やんばる急行バス） → 古宇利島 10:30着",
        "return": "古宇利島 16:30発 → バス → 那覇 19:00着",
        "time": "約2時間30分",
        "price": "約4,200円（往復）",
        "ic": "不可（現金のみ）"
      }
    },
    "budgetLevel": 3,
    "region": "九州",
    "staySupport": [
      "1night",
      "2night"
    ],
    "transportType": "air",
    "baseTravelHours": 4.5
  }
]
